hesong_ipsc_busnetcli-3.2.1.post1-py3.5-nspkg.pth
hesong/ipsc/busnetcli/__init__.py
hesong/ipsc/busnetcli/_scm_version.py
hesong/ipsc/busnetcli/_version.py
hesong/ipsc/busnetcli/client.py
hesong/ipsc/busnetcli/errors.py
hesong/ipsc/busnetcli/head.py
hesong/ipsc/busnetcli/utils.py
hesong/ipsc/busnetcli/version.py
hesong/ipsc/busnetcli/_c/__init__.py
hesong/ipsc/busnetcli/_c/helper.py
hesong/ipsc/busnetcli/_c/mutual.py
hesong/ipsc/busnetcli/_c/netapi.py
hesong/ipsc/busnetcli/data/library/Linux/x86_64/libbusnetcli.so
hesong_ipsc_busnetcli-3.2.1.post1.dist-info/METADATA
hesong_ipsc_busnetcli-3.2.1.post1.dist-info/RECORD
hesong_ipsc_busnetcli-3.2.1.post1.dist-info/WHEEL
hesong_ipsc_busnetcli-3.2.1.post1.dist-info/namespace_packages.txt
hesong_ipsc_busnetcli-3.2.1.post1.dist-info/top_level.txt
