Metadata-Version: 2.1
Name: hesong-ipsc-busnetcli
Version: 3.2.1.post1
Summary: Python wrapper for Hesong IPSC CTI Service data bus client
Home-page: https://bitbucket.org/hesong-opensource/ipsc-bus-client-python
Author: Liu Xue Yan
Author-email: liu_xue_yan@foxmail.com
License: MIT
Platform: UNKNOWN
Classifier: Development Status :: 5 - Production/Stable
Classifier: Intended Audience :: Developers
Classifier: License :: OSI Approved :: MIT License
Classifier: Programming Language :: Python :: 2
Classifier: Programming Language :: Python :: 2.6
Classifier: Programming Language :: Python :: 2.7
Classifier: Programming Language :: Python :: 3
Classifier: Programming Language :: Python :: 3.4
Classifier: Programming Language :: Python :: 3.5
Classifier: Programming Language :: Python :: 3.6
Classifier: Programming Language :: Python :: 3.7
Requires-Python: >=2.6,!=3.0.*,!=3.1.*,!=3.2.*,!=3.3.*
Requires-Dist: futures; python_version < "3.2"
Requires-Dist: enum34; python_version < "3.4"
